plank/__init__.py
plank/meta/__init__.py
plank/meta/singleton.py
plank_core-0.1.1.dist-info/LICENSE
plank_core-0.1.1.dist-info/WHEEL
plank_core-0.1.1.dist-info/METADATA
plank_core-0.1.1.dist-info/RECORD
