Metadata-Version: 2.1
Name: plank-core
Version: 0.1.1
Summary: The core function of plank.
Author: Grady Zhuo
Author-email: grady@ospark.org
Requires-Python: >=3.8,<4.0
Classifier: Programming Language :: Python :: 3
Classifier: Programming Language :: Python :: 3.8
Classifier: Programming Language :: Python :: 3.9
Classifier: Programming Language :: Python :: 3.10
Classifier: Programming Language :: Python :: 3.11
